the_pet/__init__.py
the_pet/main.py
the_pet-0.1.1.dist-info/WHEEL
the_pet-0.1.1.dist-info/METADATA
the_pet-0.1.1.dist-info/RECORD
